kerastuner/__init__.py
kerastuner/applications/__init__.py
kerastuner/distribute/__init__.py
kerastuner/engine/__init__.py
kerastuner/engine/base_tuner.py
kerastuner/engine/conditions.py
kerastuner/engine/hypermodel.py
kerastuner/engine/hyperparameters.py
kerastuner/engine/logger.py
kerastuner/engine/metrics_tracking.py
kerastuner/engine/multi_execution_tuner.py
kerastuner/engine/oracle.py
kerastuner/engine/stateful.py
kerastuner/engine/trial.py
kerastuner/engine/tuner.py
kerastuner/engine/tuner_utils.py
kerastuner/oracles/__init__.py
kerastuner/protos/__init__.py
kerastuner/tuners/__init__.py
kt_legacy-1.0.5.dist-info/LICENSE
kt_legacy-1.0.5.dist-info/METADATA
kt_legacy-1.0.5.dist-info/WHEEL
kt_legacy-1.0.5.dist-info/top_level.txt
kt_legacy-1.0.5.dist-info/RECORD
