Metadata-Version: 2.1
Name: kt-legacy
Version: 1.0.5
Summary: Legacy import names for Keras Tuner
Home-page: https://github.com/haifeng-jin/kt-legacy
Author: Haifeng Jin
License: Apache License 2.0
License-File: LICENSE
